constraint/__init__.py
constraint/constraints.c
constraint/constraints.py
constraint/domain.c
constraint/domain.py
constraint/parser.c
constraint/parser.py
constraint/problem.c
constraint/problem.py
constraint/solvers.c
constraint/solvers.py
python_constraint2-2.5.0.dist-info/licenses/LICENSE
python_constraint2-2.5.0.dist-info/METADATA
python_constraint2-2.5.0.dist-info/WHEEL
python_constraint2-2.5.0.dist-info/RECORD
