Metadata-Version: 2.4
Name: python-constraint2
Version: 2.5.0
Summary: python-constraint is a module for efficiently solving CSPs (Constraint Solving Problems) over finite domains.
License-Expression: BSD-2-Clause
License-File: LICENSE
Keywords: CSP,constraint solving problems,problem solver,SMT,satisfiability modulo theory,SAT
Author: Floris-Jan Willemsen
Author-email: fjwillemsen97@gmail.com
Maintainer: Floris-Jan Willemsen
Maintainer-email: fjwillemsen97@gmail.com
Requires-Python: >= 3.9
Classifier: Environment :: Console
Classifier: Development Status :: 5 - Production/Stable
Classifier: Intended Audience :: Developers
Classifier: Intended Audience :: Science/Research
Classifier: Intended Audience :: Education
Classifier: Natural Language :: English
Classifier: Programming Language :: C
Classifier: Programming Language :: Cython
Classifier: Topic :: Scientific/Engineering
Classifier: Topic :: Software Development
Classifier: Programming Language :: Python :: 3.9
Classifier: Programming Language :: Python :: 3.10
Classifier: Programming Language :: Python :: 3.11
Classifier: Programming Language :: Python :: 3.12
Classifier: Programming Language :: Python :: 3.13
Classifier: Programming Language :: Python :: 3.14
Project-URL: Changelog, https://github.com/python-constraint/python-constraint/blob/main/CHANGELOG.md
Project-URL: Documentation, http://python-constraint.github.io/python-constraint/
Project-URL: Homepage, http://python-constraint.github.io/python-constraint/
Project-URL: Issues, https://github.com/python-constraint/python-constraint/issues
Project-URL: Repository, https://github.com/python-constraint/python-constraint
